sqldaogenerator/common/Criterion.py
sqldaogenerator/common/CriterionDelegate.py
sqldaogenerator/common/Database.py
sqldaogenerator/common/TransactionManager.py
sqldaogenerator/common/__init__.py
sqldaogenerator/entity/General.py
sqldaogenerator/entity/Page.py
sqldaogenerator/entity/__init__.py
sqldaogenerator/entity/base.py
sqldaogenerator/generator/__init__.py
sqldaogenerator/generator/mysql_generator.py
sqldaogenerator/generator/enums/MySqlTypeEnum.py
sqldaogenerator/generator/enums/__init__.py
sqldaogenerator/generator/model/ColumnTemplate.py
sqldaogenerator/generator/model/EntityCreateReq.py
sqldaogenerator/generator/model/__init__.py
sqldaogenerator/logger/__init__.py
sqldaogenerator/logger/logger.py
sqldaogenerator/resources/BaseDaoTemplate.py
sqldaogenerator/resources/CriterionTemplate.py
sqldaogenerator/resources/DaoTemplate.py
sqldaogenerator/resources/DatasourceTemplate.py
sqldaogenerator/resources/EntityTemplate.py
sqldaogenerator/resources/TemplateTest.py
sqldaogenerator/resources/__init__.py
sqldao_generator-1.1.0.dist-info/METADATA
sqldao_generator-1.1.0.dist-info/WHEEL
sqldao_generator-1.1.0.dist-info/top_level.txt
sqldao_generator-1.1.0.dist-info/RECORD
