Metadata-Version: 2.1
Name: sqldao-generator
Version: 1.1.0
Summary: SqlAlchemy DAO generator
Home-page: https://github.com/davidhsusl/sqldao-generator
Author: Daniel Hsu
Author-email: 
Keywords: SQLAlchemy,mysql
Classifier: Programming Language :: Python :: 3
Classifier: License :: OSI Approved :: MIT License
Classifier: Operating System :: OS Independent
Requires-Python: >=3.10, <4
Requires-Dist: mysql-connector-python (<9.0.0,>=8.0.0)
Requires-Dist: SQLAlchemy (<3.0.0,>=2.0.0)
Requires-Dist: pandas (<3.0.0,>=2.0.1)
